{
  "recentFiles": [
    {
      "basename": "Carry Look Ahead Adder",
      "path": "Digital-Logic/Combinational Circuits/Carry Look Ahead Adder.md"
    },
    {
      "basename": "Pending Lectures",
      "path": "Pending Lectures.md"
    },
    {
      "basename": "Digital Logic",
      "path": "Digital-Logic/Digital Logic.md"
    },
    {
      "basename": "Ripple Carry Adder",
      "path": "Digital-Logic/Combinational Circuits/Ripple Carry Adder.md"
    },
    {
      "basename": "Half Adder and Full Adder",
      "path": "Digital-Logic/Combinational Circuits/Half Adder and Full Adder.md"
    },
    {
      "basename": "Propagation Delay and Timing Diagrams",
      "path": "Digital-Logic/Combinational Circuits/Propagation Delay and Timing Diagrams.md"
    },
    {
      "basename": "Decoder",
      "path": "Digital-Logic/Combinational Circuits/Decoder.md"
    },
    {
      "basename": "Encoder",
      "path": "Digital-Logic/Combinational Circuits/Encoder.md"
    },
    {
      "basename": "Minimization using K Map",
      "path": "Digital-Logic/Boolean Algebra-Minimization of Boolean Functions/Minimization using K Map.md"
    },
    {
      "basename": "Multiplexer and Demultiplexer",
      "path": "Digital-Logic/Combinational Circuits/Multiplexer and Demultiplexer.md"
    },
    {
      "basename": "Logical Connectives",
      "path": "DiscreteMathematics/Propositional-Logic/Logical Connectives.md"
    },
    {
      "basename": "Negation",
      "path": "DiscreteMathematics/Propositional-Logic/Negation.md"
    },
    {
      "basename": "Discrete Mathematics",
      "path": "DiscreteMathematics/Discrete Mathematics.md"
    },
    {
      "basename": "Propositional Logic",
      "path": "DiscreteMathematics/Propositional-Logic/Propositional Logic.md"
    },
    {
      "basename": "Compact Truth Table Representation",
      "path": "Digital-Logic/Combinational Circuits/Compact Truth Table Representation.md"
    },
    {
      "basename": "Basic Concepts of TOC",
      "path": "TheoryOfComputation/Regular Languages and Finite Automata/Basic Concepts of TOC.md"
    },
    {
      "basename": "Countability Results in Theory of Computation",
      "path": "TheoryOfComputation/Countability/Countability Results in Theory of Computation.md"
    },
    {
      "basename": "Theory of Computation",
      "path": "TheoryOfComputation/Theory of Computation.md"
    },
    {
      "basename": "Uncountable Sets",
      "path": "TheoryOfComputation/Countability/Uncountable Sets.md"
    },
    {
      "basename": "Countable Sets",
      "path": "TheoryOfComputation/Countability/Countable Sets.md"
    },
    {
      "basename": "Cantor's Theorem",
      "path": "TheoryOfComputation/Countability/Cantor's Theorem.md"
    },
    {
      "basename": "Theorems for Countable Sets",
      "path": "TheoryOfComputation/Countability/Theorems for Countable Sets.md"
    },
    {
      "basename": "Binary Codes",
      "path": "Digital-Logic/Number Systems/Binary Codes.md"
    },
    {
      "basename": "Gray code",
      "path": "Digital-Logic/Number Systems/Gray code.md"
    },
    {
      "basename": "Temporary Plan",
      "path": "Temporary Plan.md"
    },
    {
      "basename": "Verbal-Ability",
      "path": "Aptitude/Verbal-Ability/Verbal-Ability.md"
    },
    {
      "basename": "Sign Extension",
      "path": "Digital-Logic/Number Systems/Sign Extension.md"
    },
    {
      "basename": "Signed Binary Numbers",
      "path": "Digital-Logic/Number Systems/Signed Binary Numbers.md"
    },
    {
      "basename": "Overflow",
      "path": "Digital-Logic/Number Systems/Overflow.md"
    },
    {
      "basename": "Aptitude",
      "path": "Aptitude/Aptitude.md"
    },
    {
      "basename": "Number System",
      "path": "Aptitude/Quantitative-Aptitude/Number System.md"
    },
    {
      "basename": "Addition of Signed Binary Numbers",
      "path": "Digital-Logic/Number Systems/Addition of Signed Binary Numbers.md"
    },
    {
      "basename": "Introduction to Digital Logic",
      "path": "Digital-Logic/Boolean Algebra-Minimization of Boolean Functions/Introduction to Digital Logic.md"
    },
    {
      "basename": "Complements in Number System",
      "path": "Digital-Logic/Number Systems/Complements in Number System.md"
    },
    {
      "basename": "Subtraction of Unsigned Numbers",
      "path": "Digital-Logic/Number Systems/Subtraction of Unsigned Numbers.md"
    },
    {
      "basename": "GATE-CS",
      "path": "GATE-CS.md"
    },
    {
      "basename": "2's complement",
      "path": "C/Binary and 2'complements/2's complement.md"
    },
    {
      "basename": "Binary System",
      "path": "Digital-Logic/Number Systems/Binary System.md"
    },
    {
      "basename": "Decimal and Binary System",
      "path": "Digital-Logic/Boolean Algebra-Minimization of Boolean Functions/Decimal and Binary System.md"
    },
    {
      "basename": "Number Systems",
      "path": "Digital-Logic/Number Systems/Number Systems.md"
    },
    {
      "basename": "Octal and Hexadecimal System",
      "path": "Digital-Logic/Number Systems/Octal and Hexadecimal System.md"
    },
    {
      "basename": "Understanding Infinity and Cardinality",
      "path": "TheoryOfComputation/Countability/Understanding Infinity and Cardinality.md"
    },
    {
      "basename": "Function Definition",
      "path": "DiscreteMathematics/Functions/Function Definition.md"
    },
    {
      "basename": "Types of Functions",
      "path": "DiscreteMathematics/Functions/Types of Functions.md"
    },
    {
      "basename": "Boolean Function",
      "path": "Digital-Logic/Boolean Algebra-Minimization of Boolean Functions/Boolean Function.md"
    },
    {
      "basename": "Laws of Boolean Algebra",
      "path": "Digital-Logic/Boolean Algebra-Minimization of Boolean Functions/Laws of Boolean Algebra.md"
    },
    {
      "basename": "Algebraic Simplification of Boolean Functions",
      "path": "Digital-Logic/Boolean Algebra-Minimization of Boolean Functions/Algebraic Simplification of Boolean Functions.md"
    },
    {
      "basename": "Standard and Canonical Forms of Boolean Expressions",
      "path": "Digital-Logic/Boolean Algebra-Minimization of Boolean Functions/Standard and Canonical Forms of Boolean Expressions.md"
    },
    {
      "basename": "Implicants in K Map",
      "path": "Digital-Logic/Boolean Algebra-Minimization of Boolean Functions/Implicants in K Map.md"
    },
    {
      "basename": "Unless",
      "path": "DiscreteMathematics/Propositional-Logic/Unless.md"
    }
  ],
  "omittedPaths": [
    ""
  ],
  "maxLength": null,
  "openType": "tab"
}